digi_solver/__init__.py
digi_solver/kmap_tool/__init__.py
digi_solver/kmap_tool/gen_kmap.py
digi_solver/kmap_tool/QuineMcCluskey/__init__.py
digi_solver/kmap_tool/QuineMcCluskey/qmccluskey.py
digi_solver/kmap_tool/QuineMcCluskey/core/__init__.py
digi_solver/kmap_tool/QuineMcCluskey/core/qm/__init__.py
digi_solver/kmap_tool/QuineMcCluskey/core/qm/petrick.py
digi_solver/kmap_tool/QuineMcCluskey/core/qm/qm.py
digi_solver/lo_gateimg_tool/__init__.py
digi_solver/lo_gateimg_tool/kmap.py
digi_solver/lo_gateimg_tool/test_circuit_generation.py
digi_solver/lo_gateimg_tool/test_kmap_module.py
digi_solver/lo_gateimg_tool/digicircuit/__init__.py
digi_solver/lo_gateimg_tool/digicircuit/boolean_parser.py
digi_solver/lo_gateimg_tool/digicircuit/boolean_to_circuit.py
digi_solver/lo_gateimg_tool/digicircuit/circuit.py
digi_solver/lo_gateimg_tool/digicircuit/cli.py
digi_solver/lo_gateimg_tool/digicircuit/gate.py
digi_solver/lo_gateimg_tool/digicircuit/latex_export.py
digi_solver/ncalc_python/__init__.py
digi_solver/ncalc_python/cli.py
digi_solver/ncalc_python/config.py
digi_solver/ncalc_python/conversions.py
digi_solver/ncalc_python/file_processor.py
digi_solver/ncalc_python/ncalc.py
digi_solver/ncalc_python/step_generator.py
digi_solver/ncalc_python/utils.py
digi_solver/signed_binary_conversion/__init__.py
digi_solver/signed_binary_conversion/binary_converter.py
digi_solver/signed_binary_conversion/binary_to_decimal.py
digi_solver/signed_binary_conversion/decimal_to_binary.py
digi_solver/signed_binary_conversion/solutions/__init__.py
digi_solver/signed_binary_conversion/solutions/b2d_solutions.py
digi_solver/signed_binary_conversion/solutions/d2b_solutions.py
digi_solver-0.2.0.dist-info/METADATA
digi_solver-0.2.0.dist-info/WHEEL
digi_solver-0.2.0.dist-info/entry_points.txt
digi_solver-0.2.0.dist-info/top_level.txt
digi_solver-0.2.0.dist-info/RECORD
