Metadata-Version: 2.4
Name: digi_solver
Version: 0.2.0
Summary: A Python package for digital electronics problem solving, including K-maps, number conversions, and more.
Home-page: https://github.com/19uez
Author: 19uez
Author-email: phaman5109@gmail.com
Classifier: Development Status :: 3 - Alpha
Classifier: Intended Audience :: Developers
Classifier: Intended Audience :: Education
Classifier: Intended Audience :: Science/Research
Classifier: License :: OSI Approved :: MIT License
Classifier: Programming Language :: Python :: 3
Classifier: Programming Language :: Python :: 3.7
Classifier: Programming Language :: Python :: 3.8
Classifier: Operating System :: OS Independent
Classifier: Topic :: Education
Classifier: Topic :: Scientific/Engineering
Classifier: Topic :: Software Development :: Libraries :: Python Modules
Requires-Python: ==3.8
Requires-Dist: numpy
Requires-Dist: pandas
Requires-Dist: openpyxl
Requires-Dist: Pillow
Requires-Dist: requests
Requires-Dist: colorclass
Requires-Dist: terminaltables
Dynamic: author
Dynamic: author-email
Dynamic: classifier
Dynamic: description
Dynamic: description-content-type
Dynamic: home-page
Dynamic: requires-dist
Dynamic: requires-python
Dynamic: summary
